sigx/__init__.py
sigx-3.0.0.dist-info/METADATA
sigx-3.0.0.dist-info/WHEEL
sigx-3.0.0.dist-info/top_level.txt
sigx-3.0.0.dist-info/RECORD
