Metadata-Version: 2.1
Name: sigx
Version: 3.0.0
Summary: Async in-memory topic-pattern signal exchange
Home-page: https://github.com/ConnorSMaynes/sigx
Author: Connor Sherwood Maynes
Author-email: connormaynes@gmail.com
License: MIT
Keywords: topic-pattern,topic,signal,event,blinker
Classifier: Programming Language :: Python :: 3
Classifier: Operating System :: OS Independent
Requires-Python: <4,>=3.5
Requires-Dist: refutil (<2,>=1)
Requires-Dist: anyio (>=3)
